locallm/__init__.py
locallm/provider.py
locallm/schemas.py
locallm/providers/__init__.py
locallm/providers/koboldcpp.py
locallm/providers/local.py
locallm/providers/ollama.py
locallm-0.5.3.dist-info/LICENCE.txt
locallm-0.5.3.dist-info/METADATA
locallm-0.5.3.dist-info/WHEEL
locallm-0.5.3.dist-info/top_level.txt
locallm-0.5.3.dist-info/zip-safe
locallm-0.5.3.dist-info/RECORD
