Metadata-Version: 2.1
Name: locallm
Version: 0.5.3
Summary: An api to query local language models using different backends
Home-page: https://github.com/emencia/locallm
Author: emencia
Author-email: contact@emencia.com
License: MIT
Project-URL: Source Code, https://github.com/emencia/locallm
Project-URL: Issue Tracker, https://github.com/emencia/locallm/issues
Keywords: Python
Classifier: Development Status :: 2 - Pre-Alpha
Classifier: Intended Audience :: Developers
Classifier: License :: OSI Approved :: MIT License
Classifier: Natural Language :: English
Classifier: Programming Language :: Python :: 3
Classifier: Programming Language :: Python :: 3.8
Classifier: Programming Language :: Python :: 3.9
Classifier: Programming Language :: Python :: 3.10
License-File: LICENCE.txt
Requires-Dist: pydantic
Requires-Dist: requests
Requires-Dist: sseclient-py
Requires-Dist: llama-cpp-python
Provides-Extra: dev
Requires-Dist: pytest ; extra == 'dev'
Provides-Extra: quality
Requires-Dist: flake8 ; extra == 'quality'
Requires-Dist: tox ; extra == 'quality'
Requires-Dist: twine ; extra == 'quality'
